snipy/__init__.py
snipy/activeq.py
snipy/ansi.py
snipy/basic.py
snipy/caller.py
snipy/common.py
snipy/concurrent.py
snipy/cuda.py
snipy/database.py
snipy/decotool.py
snipy/dictobj.py
snipy/enum.py
snipy/flags.py
snipy/ilogging.py
snipy/imageme.py
snipy/irandom.py
snipy/iterflow.py
snipy/jsonutil.py
snipy/listx.py
snipy/matplotlib_background.py
snipy/named.py
snipy/odict.py
snipy/packageutil.py
snipy/progress.py
snipy/queues.py
snipy/scope_factory.py
snipy/sizeof.py
snipy/stringutil.py
snipy/term.py
snipy/this_package.py
snipy/tictoc.py
snipy/img/__init__.py
snipy/img/imageutil.py
snipy/io/__init__.py
snipy/io/fileutil.py
snipy/plt/__init__.py
snipy/plt/cmap.py
snipy/plt/ploting.py
snipy/train/__init__.py
snipy/train/crossvalidation_set.py
snipy-0.0.6.dist-info/DESCRIPTION.rst
snipy-0.0.6.dist-info/METADATA
snipy-0.0.6.dist-info/RECORD
snipy-0.0.6.dist-info/WHEEL
snipy-0.0.6.dist-info/metadata.json
snipy-0.0.6.dist-info/top_level.txt
tests/__init__.py
tests/test_odict.py
