Metadata-Version: 2.0
Name: snipy
Version: 0.0.6
Summary: python utility @ your own risk
Home-page: https://github.com/dade-ai/snipy
Author: dade
Author-email: aiplore@gmail.com
License: MIT
Platform: UNKNOWN
Classifier: Development Status :: 3 - Alpha
Classifier: Intended Audience :: Developers
Classifier: License :: OSI Approved :: MIT License
Classifier: Programming Language :: Python :: 3.6
Provides-Extra: perlin
Provides-Extra: cuda
Provides-Extra: image
Provides-Extra: plot
Provides-Extra: sizeof
Provides-Extra: all
Provides-Extra: json
Provides-Extra: h5
Provides-Extra: file
Requires-Dist: numpy
Requires-Dist: setuptools
Provides-Extra: all
Requires-Dist: Jinja2; extra == 'all'
Provides-Extra: cuda
Requires-Dist: pycuda; extra == 'cuda'
Provides-Extra: file
Requires-Dist: joblib; extra == 'file'
Requires-Dist: scandir; extra == 'file'
Provides-Extra: h5
Requires-Dist: h5py; extra == 'h5'
Provides-Extra: image
Requires-Dist: scikit-image; extra == 'image'
Requires-Dist: Pillow; extra == 'image'
Requires-Dist: scikit-image; extra == 'image'
Provides-Extra: json
Requires-Dist: ujson; extra == 'json'
Provides-Extra: perlin
Requires-Dist: noise; extra == 'perlin'
Provides-Extra: plot
Requires-Dist: scikit-image; extra == 'plot'
Requires-Dist: matplotlib; extra == 'plot'
Provides-Extra: sizeof
Requires-Dist: pympler; extra == 'sizeof'
